CHANGES.rst
MANIFEST.in
README.rst
buildout.cfg
setup.py
plonetheme/__init__.py
plonetheme/__init__.pyc
plonetheme.diazo_sunburst.egg-info/PKG-INFO
plonetheme.diazo_sunburst.egg-info/SOURCES.txt
plonetheme.diazo_sunburst.egg-info/dependency_links.txt
plonetheme.diazo_sunburst.egg-info/entry_points.txt
plonetheme.diazo_sunburst.egg-info/namespace_packages.txt
plonetheme.diazo_sunburst.egg-info/not-zip-safe
plonetheme.diazo_sunburst.egg-info/requires.txt
plonetheme.diazo_sunburst.egg-info/top_level.txt
plonetheme/diazo_sunburst/__init__.py
plonetheme/diazo_sunburst/__init__.pyc
plonetheme/diazo_sunburst/configure.zcml
plonetheme/diazo_sunburst/tests.py
plonetheme/diazo_sunburst/profiles/default/metadata.xml
plonetheme/diazo_sunburst/profiles/default/theme.xml
plonetheme/diazo_sunburst/theme/index.html
plonetheme/diazo_sunburst/theme/manifest.cfg
plonetheme/diazo_sunburst/theme/rules.xml
plonetheme/diazo_sunburst/theme/css/IEFixes.css
plonetheme/diazo_sunburst/theme/css/RTL.css
plonetheme/diazo_sunburst/theme/css/authoring.css
plonetheme/diazo_sunburst/theme/css/base.css
plonetheme/diazo_sunburst/theme/css/columns.css
plonetheme/diazo_sunburst/theme/css/contenttypes-sprite.png
plonetheme/diazo_sunburst/theme/css/controlpanel.css
plonetheme/diazo_sunburst/theme/css/deprecated.css
plonetheme/diazo_sunburst/theme/css/dropdown-menu.css
plonetheme/diazo_sunburst/theme/css/forms.css
plonetheme/diazo_sunburst/theme/css/invisibles.css
plonetheme/diazo_sunburst/theme/css/kupuplone.css
plonetheme/diazo_sunburst/theme/css/member.css
plonetheme/diazo_sunburst/theme/css/mobile.css
plonetheme/diazo_sunburst/theme/css/navtree.css
plonetheme/diazo_sunburst/theme/css/ploneCustom.css
plonetheme/diazo_sunburst/theme/css/portlets.css
plonetheme/diazo_sunburst/theme/css/print.css
plonetheme/diazo_sunburst/theme/css/public.css
plonetheme/diazo_sunburst/theme/css/reset.css
plonetheme/diazo_sunburst/theme/images/Preparation_of_diazomalonic_acid_ester_by_Dimroth.svg
plonetheme/diazo_sunburst/theme/images/contenttypes-sprite.png
plonetheme/diazo_sunburst/theme/images/favicon.ico
plonetheme/diazo_sunburst/theme/images/logo.png
plonetheme/diazo_sunburst/theme/images/preview.png
plonetheme/diazo_sunburst/theme/images/touch_icon.png
plonetheme/diazo_sunburst/theme/js/accessibility.js
plonetheme/diazo_sunburst/theme/js/calendar_formfield.js
