Metadata-Version: 1.1
Name: plonetheme.diazo-sunburst
Version: 0.1.2
Summary: Plone 4's default Sunburst theme reimplemented in Diazo
Home-page: https://github.com/collective/plonetheme.diazo_sunburst
Author: Alex Clark
Author-email: aclark@aclark.net
License: GPL2
Keywords: Diazo Modern Plone Sunburst Theme Theming
Platform: UNKNOWN
Classifier: Framework :: Plone :: 4.3
Classifier: Programming Language :: Python :: 2.7
